{
  "ADX": "SqADX",
  "ATR": "SqATR",
  "Aroon": "SqAroon",
  "AwesomeOscillator": "Awesome_Oscillator",
  "BHErgodic": "SqBHErgodic",
  "BearsPower": "SqBearsPower",
  "BollingerBands": "BB",
  "BollingerBandsPercentB": "SqBollingerBandsPercentB",
  "BullsPower": "SqBullsPower",
  "CCI": "SqCCI",
  "CMMA": "SqCMMA",
  "CRSI": "SqConnorsRSI",
  "CSSAMarketRegime": "SqCSSARegime",
  "CaseyCPercent": "SqCaseyCPercent",
  "ChoppinessIndex": "SqChoppinessIndex",
  "DPO": "SqDPO",
  "DSSBressert": "SqDSSBressert",
  "DeMarker": "DeMarker",
  "DidiIndex": "SqDidiIndex",
  "DisparityIndex": "SqDisparityIndex",
  "DonchianChannels": "SqDonchianChannels",
  "EMA": "MA",
  "EntropyMath": "SqEntropyMath",
  "Fibo": "SqFibo",
  "Fractal": "SqFractal",
  "GannHiLo": "SqGannHiLo",
  "Highest": "SqHighest",
  "HighestInRange": "SqHighestInRange",
  "HullMovingAverage": "SqHullMovingAverage",
  "HullMovingAverageBollingerBands": "SqHullMovingAverageBollingerBands",
  "HurstExponent": "SqHurstExponent",
  "Ichimoku": "Ichimoku",
  "KAMA": "SqKAMA",
  "KAMAOhlc": "SqKAMAOhlc",
  "KaufmanEfficiencyRatio": "SqEfficiencyRatio",
  "KeltnerChannel": "KC",
  "KolmogorovSmirnovTest": "SqKolmogorovSmirnovTest",
  "LWMA": "LWMA",
  "LaguerreRSI": "SqLaguerreRSI",
  "LinearRegression": "SqLinReg",
  "LogATR": "SqLogATR",
  "Lowest": "SqLowest",
  "LowestInRange": "SqLowestInRange",
  "MACD": "MACD",
  "MTKeltnerChannel": "SqMTKeltnerChannel",
  "Momentum": "Momentum",
  "OSMA": "OsMA",
  "ParabolicSAR": "ParabolicSAR",
  "Pivots": "SqPivots",
  "QQE": "SqQQE",
  "ROC": "ROC",
  "RSI": "RSI",
  "RVI": "RVI",
  "Reflex": "SqReflex",
  "SMA": "SMA",
  "SMMA": "SMMA",
  "SRPercentRank": "SqSRPercentRank",
  "SSL": "SqSSL",
  "SchaffTrendCycle": "SqSchaffTrendCycle",
  "SlopeDirectionLine": "SqSlopeDirectionLine",
  "SmoothedRSI": "SqSmoothedRSI",
  "StdDev": "StdDev",
  "Stochastic": "SqStochastic",
  "SuperTrend": "SqSuperTrend",
  "TEMA": "TEMA",
  "TrueRange": "SqTrueRange",
  "UlcerIndex": "SqUlcerIndex",
  "UltimateC": "SqUltimateC",
  "UltimateOscillator": "Ultimate_Oscillator",
  "VMA": "SqVMA",
  "VST": "SqVST",
  "Vortex": "SqVortex",
  "WAE": "SqWAE",
  "WilliamsPR": "SqWpr",
  "ZScore": "SqZScore"
}